latint/__init__.py
latint/clustering.py
latint/input_feature_variance.py
latint/interact_functions.py
latint/load.py
latint/plotCorrelation.py
latint/plotLatentDistributions.py
latint/sampling.py
LatInt-0.1.0.dist-info/METADATA
LatInt-0.1.0.dist-info/WHEEL
LatInt-0.1.0.dist-info/top_level.txt
LatInt-0.1.0.dist-info/RECORD
