Metadata-Version: 2.1
Name: LatInt
Version: 0.1.0
Summary: Collection of modules to easily interpret Deep Learned latent spaces
Home-page: https://github.com/sifrimlab/LatInt
Author: LMIB
Author-email: david.wouters@kuleuven.be
Project-URL: Bug Reports, https://github.com/sifrimlab/LatInt
Project-URL: Source, https://github.com/sifrimlab/LatInt
Keywords: deep-learning
Classifier: Development Status :: 3 - Alpha
Classifier: Topic :: Scientific/Engineering :: Bio-Informatics
Classifier: License :: OSI Approved :: GNU Affero General Public License v3
Classifier: Programming Language :: Python :: 3
Classifier: Programming Language :: Python :: 3.0
Requires-Python: >=3.9
Requires-Dist: numpy
Requires-Dist: pandas
Requires-Dist: tqdm
Requires-Dist: matplotlib
Requires-Dist: torch
Requires-Dist: scanpy
Requires-Dist: anndata (==0.8)
